plastexshowmore/__init__.py
plastexshowmore/Packages/showmore.py
plastexshowmore/static/js.cookie.min.js
plastexshowmore/static/showmore.css
plastexshowmore/static/showmore.js
plastexshowmore-0.0.2.dist-info/LICENSE
plastexshowmore-0.0.2.dist-info/METADATA
plastexshowmore-0.0.2.dist-info/WHEEL
plastexshowmore-0.0.2.dist-info/top_level.txt
plastexshowmore-0.0.2.dist-info/RECORD
