Metadata-Version: 2.1
Name: plastexshowmore
Version: 0.0.2
Summary: Show more buttons for plasTeX.
Home-page: https://github.com/PatrickMassot/plastexshowmore
Author: Patrick Massot
Classifier: Programming Language :: Python :: 3
Classifier: License :: OSI Approved :: MIT License
Classifier: Operating System :: OS Independent
Requires-Python: >=3.7
License-File: LICENSE
Requires-Dist: plasTeX>=3.1
